nbnovnc/__init__.py
nbnovnc/handlers.py
nbnovnc/static/tree.js
nbnovnc-0.1.1.dist-info/DESCRIPTION.rst
nbnovnc-0.1.1.dist-info/METADATA
nbnovnc-0.1.1.dist-info/RECORD
nbnovnc-0.1.1.dist-info/WHEEL
nbnovnc-0.1.1.dist-info/metadata.json
nbnovnc-0.1.1.dist-info/top_level.txt
