Metadata-Version: 2.0
Name: nbnovnc
Version: 0.1.1
Summary: Jupyter extension to proxy a VNC session via noVNC
Home-page: https://github.com/ryanlovett/nbnovnc
Author: Ryan Lovett
Author-email: rylo@berkeley.edu
License: UNKNOWN
Keywords: Jupyter
Platform: UNKNOWN
Classifier: Framework :: Jupyter
Requires-Dist: pyzmq (>=17)
Requires-Dist: tornado (>=5)
Requires-Dist: notebook
Requires-Dist: nbserverproxy (>=0.8.1)
